atolibrary/__init__.py
atolibrary/file.py
atolibrary/image.py
atolibrary/lotto.py
atolibrary/names.py
atolibrary-0.0.14.dist-info/METADATA
atolibrary-0.0.14.dist-info/WHEEL
atolibrary-0.0.14.dist-info/top_level.txt
atolibrary-0.0.14.dist-info/RECORD
