Metadata-Version: 2.1
Name: atolibrary
Version: 0.0.14
Summary: A utility library for image processing and random number generation
Home-page: https://github.com/attojeon/atolibrary
Author: ATO JEON
Author-email: atto.jeon@gmail.com
Classifier: Programming Language :: Python :: 3
Classifier: License :: OSI Approved :: MIT License
Classifier: Operating System :: OS Independent
Requires-Python: >=3.6
Requires-Dist: Pillow (>=9.0.0)
Requires-Dist: requests
Requires-Dist: faker
